nominet_dac/__init__.py
nominet_dac/__main__.py
nominet_dac/dac.py
nominet_dac/token_bucket.py
nominet_dac-0.1.dist-info/METADATA
nominet_dac-0.1.dist-info/WHEEL
nominet_dac-0.1.dist-info/top_level.txt
nominet_dac-0.1.dist-info/RECORD
