Metadata-Version: 2.1
Name: nominet-dac
Version: 0.1
Summary: UNKNOWN
Home-page: https://github.com/matthewashby/DS-Nominet-DAC
Author: DS
Author-email: matt@ashby.co.uk
License: NA
Platform: UNKNOWN
Requires-Dist: gevent
